gensty/__init__.py
gensty/__main__.py
gensty/cli.py
gensty/config.py
gensty/font.py
gensty/helpers.py
gensty-0.3.1.dist-info/LICENSE
gensty-0.3.1.dist-info/METADATA
gensty-0.3.1.dist-info/WHEEL
gensty-0.3.1.dist-info/entry_points.txt
gensty-0.3.1.dist-info/top_level.txt
gensty-0.3.1.dist-info/RECORD
