Metadata-Version: 2.1
Name: gensty
Version: 0.3.1
Summary: LaTex style generator for ttf/otf fonts. Supports Smufl.
Home-page: UNKNOWN
Author: Georgios Tsotsos
Author-email: tsotsos@gmail.com
License: GPL-2.0 License
Project-URL: Documentation, https://gensty.readthedocs.io/
Project-URL: Source, https://github.com/tsotsos/gensty
Keywords: latex generator package fonts
Platform: UNKNOWN
Classifier: Development Status :: 5 - Production/Stable
Classifier: Environment :: Console
Classifier: Intended Audience :: Education
Classifier: Intended Audience :: Developers
Classifier: Intended Audience :: End Users/Desktop
Classifier: Intended Audience :: Science/Research
Classifier: Intended Audience :: Information Technology
Classifier: Topic :: Text Processing :: Markup :: LaTeX
Classifier: License :: OSI Approved :: GNU General Public License v2 (GPLv2)
Classifier: Natural Language :: English
Classifier: Programming Language :: Python :: 3.5
Classifier: Programming Language :: Python :: 3.6
Classifier: Programming Language :: Python :: 3.8
Requires-Python: >=3
Requires-Dist: fontTools
